{"basename":"ice","fileperms":"0777","filetype":"dir","is_writeable":true,"is_readable":true,"is_link":false,"mime":"directory","mtime":1630063509,"path":"spell-effects/ice","dirsize":31433300,"files_count":13,"images_count":null,"files":{"frost-RECTANGLE_01.webm":{"basename":"frost-RECTANGLE_01.webm","fileperms":"0666","filetype":"file","filesize":6659136,"is_readable":true,"is_writeable":true,"is_link":false,"mtime":1630063508,"path":"spell-effects/ice/frost-RECTANGLE_01.webm","ext":"webm"},"frost-SQUARE_01.webm":{"basename":"frost-SQUARE_01.webm","fileperms":"0666","filetype":"file","filesize":4723102,"is_readable":true,"is_writeable":true,"is_link":false,"mtime":1630063508,"path":"spell-effects/ice/frost-SQUARE_01.webm","ext":"webm"},"frost_beam_RAY_01.webm":{"basename":"frost_beam_RAY_01.webm","fileperms":"0666","filetype":"file","filesize":2827610,"is_readable":true,"is_writeable":true,"is_link":false,"mtime":1630063509,"path":"spell-effects/ice/frost_beam_RAY_01.webm","ext":"webm"},"frost_beam_RAY_02.webm":{"basename":"frost_beam_RAY_02.webm","fileperms":"0666","filetype":"file","filesize":974333,"is_readable":true,"is_writeable":true,"is_link":false,"mtime":1630063509,"path":"spell-effects/ice/frost_beam_RAY_02.webm","ext":"webm"},"frost_CONE_01.webm":{"basename":"frost_CONE_01.webm","fileperms":"0666","filetype":"file","filesize":701478,"is_readable":true,"is_writeable":true,"is_link":false,"mtime":1630063508,"path":"spell-effects/ice/frost_CONE_01.webm","ext":"webm"},"frost_CONE_02.webm":{"basename":"frost_CONE_02.webm","fileperms":"0666","filetype":"file","filesize":767325,"is_readable":true,"is_writeable":true,"is_link":false,"mtime":1630063508,"path":"spell-effects/ice/frost_CONE_02.webm","ext":"webm"},"frost_CONE_03.webm":{"basename":"frost_CONE_03.webm","fileperms":"0666","filetype":"file","filesize":745773,"is_readable":true,"is_writeable":true,"is_link":false,"mtime":1630063508,"path":"spell-effects/ice/frost_CONE_03.webm","ext":"webm"},"frost_CONE_04.webm":{"basename":"frost_CONE_04.webm","fileperms":"0666","filetype":"file","filesize":1005975,"is_readable":true,"is_writeable":true,"is_link":false,"mtime":1630063508,"path":"spell-effects/ice/frost_CONE_04.webm","ext":"webm"},"frost_CONE_05.webm":{"basename":"frost_CONE_05.webm","fileperms":"0666","filetype":"file","filesize":720410,"is_readable":true,"is_writeable":true,"is_link":false,"mtime":1630063508,"path":"spell-effects/ice/frost_CONE_05.webm","ext":"webm"},"frost_CONE_06.webm":{"basename":"frost_CONE_06.webm","fileperms":"0666","filetype":"file","filesize":485974,"is_readable":true,"is_writeable":true,"is_link":false,"mtime":1630063508,"path":"spell-effects/ice/frost_CONE_06.webm","ext":"webm"},"frost_CONE_07.webm":{"basename":"frost_CONE_07.webm","fileperms":"0666","filetype":"file","filesize":700971,"is_readable":true,"is_writeable":true,"is_link":false,"mtime":1630063508,"path":"spell-effects/ice/frost_CONE_07.webm","ext":"webm"},"ice_ball_RAY_01.webm":{"basename":"ice_ball_RAY_01.webm","fileperms":"0666","filetype":"file","filesize":412940,"is_readable":true,"is_writeable":true,"is_link":false,"mtime":1630063509,"path":"spell-effects/ice/ice_ball_RAY_01.webm","ext":"webm"},"ice_shield_rotating_SQUARE_01.webm":{"basename":"ice_shield_rotating_SQUARE_01.webm","fileperms":"0666","filetype":"file","filesize":10708273,"is_readable":true,"is_writeable":true,"is_link":false,"mtime":1630063509,"path":"spell-effects/ice/ice_shield_rotating_SQUARE_01.webm","ext":"webm"}}}