{"basename":"Night","fileperms":"0777","filetype":"dir","is_writeable":true,"is_readable":true,"is_link":false,"mime":"directory","mtime":1617628381,"path":"Neutral Maps (April 2021)/Great Tree Clearing/Night","dirsize":9544356,"files_count":3,"images_count":2,"files":{"Great_Tree_Clearing_Night.jpg":{"basename":"Great_Tree_Clearing_Night.jpg","fileperms":"0666","filetype":"file","filesize":3522571,"is_readable":true,"is_writeable":true,"is_link":false,"mtime":1589320107,"path":"Neutral Maps (April 2021)/Great Tree Clearing/Night/Great_Tree_Clearing_Night.jpg","ext":"jpg","icon":"image","mime":"image/jpeg","image":{"width":2775,"height":2775,"type":2,"bits":8,"channels":3,"mime":"image/jpeg"}},"Great_Tree_Clearing_Night.pdf":{"basename":"Great_Tree_Clearing_Night.pdf","fileperms":"0666","filetype":"file","filesize":2696937,"is_readable":true,"is_writeable":true,"is_link":false,"mtime":1589320125,"path":"Neutral Maps (April 2021)/Great Tree Clearing/Night/Great_Tree_Clearing_Night.pdf","ext":"pdf"},"Great_Tree_Clearing_Night_Gridless.jpg":{"basename":"Great_Tree_Clearing_Night_Gridless.jpg","fileperms":"0666","filetype":"file","filesize":3324848,"is_readable":true,"is_writeable":true,"is_link":false,"mtime":1589320140,"path":"Neutral Maps (April 2021)/Great Tree Clearing/Night/Great_Tree_Clearing_Night_Gridless.jpg","ext":"jpg","icon":"image","mime":"image/jpeg","image":{"width":2775,"height":2775,"type":2,"bits":8,"channels":3,"mime":"image/jpeg"}}}}