{"basename":"beast","fileperms":"0777","filetype":"dir","is_writeable":true,"is_readable":true,"is_link":false,"mime":"directory","mtime":1630063629,"path":"","dirsize":null,"files_count":null,"images_count":null,"files":{"animated-spell-effects":{"basename":"animated-spell-effects","fileperms":"0777","filetype":"dir","filesize":false,"is_readable":true,"is_writeable":true,"is_link":false,"mtime":1630063636,"path":"animated-spell-effects","mime":"directory"},"Bestiary 1":{"basename":"Bestiary 1","fileperms":"0777","filetype":"dir","filesize":false,"is_readable":true,"is_writeable":true,"is_link":false,"mtime":1617567942,"path":"Bestiary 1","mime":"directory"},"Bestiary 2":{"basename":"Bestiary 2","fileperms":"0777","filetype":"dir","filesize":false,"is_readable":true,"is_writeable":true,"is_link":false,"mtime":1617289761,"path":"Bestiary 2","mime":"directory"},"Bestiary 3":{"basename":"Bestiary 3","fileperms":"0777","filetype":"dir","filesize":false,"is_readable":true,"is_writeable":true,"is_link":false,"mtime":1617121430,"path":"Bestiary 3","mime":"directory"},"Bestiary 4":{"basename":"Bestiary 4","fileperms":"0777","filetype":"dir","filesize":false,"is_readable":true,"is_writeable":true,"is_link":false,"mtime":1617133754,"path":"Bestiary 4","mime":"directory"},"Bestiary 5":{"basename":"Bestiary 5","fileperms":"0777","filetype":"dir","filesize":false,"is_readable":true,"is_writeable":true,"is_link":false,"mtime":1617133655,"path":"Bestiary 5","mime":"directory"},"Bestiary 6":{"basename":"Bestiary 6","fileperms":"0777","filetype":"dir","filesize":false,"is_readable":true,"is_writeable":true,"is_link":false,"mtime":1617153785,"path":"Bestiary 6","mime":"directory"},"Goblin":{"basename":"Goblin","fileperms":"0777","filetype":"dir","filesize":false,"is_readable":true,"is_writeable":true,"is_link":false,"mtime":1617153335,"path":"Goblin","mime":"directory"},"Goblins of Golarion":{"basename":"Goblins of Golarion","fileperms":"0777","filetype":"dir","filesize":false,"is_readable":true,"is_writeable":true,"is_link":false,"mtime":1617326059,"path":"Goblins of Golarion","mime":"directory"},"Inner Sea Bestiary":{"basename":"Inner Sea Bestiary","fileperms":"0777","filetype":"dir","filesize":false,"is_readable":true,"is_writeable":true,"is_link":false,"mtime":1617289650,"path":"Inner Sea Bestiary","mime":"directory"},"Meditating Munky's Roll20 AoE Spell Templates":{"basename":"Meditating Munky's Roll20 AoE Spell Templates","fileperms":"0777","filetype":"dir","filesize":false,"is_readable":true,"is_writeable":true,"is_link":false,"mtime":1623260241,"path":"Meditating Munky's Roll20 AoE Spell Templates","mime":"directory"},"Neutral Maps (April 2021)":{"basename":"Neutral Maps (April 2021)","fileperms":"0777","filetype":"dir","filesize":false,"is_readable":true,"is_writeable":true,"is_link":false,"mtime":1617628577,"path":"Neutral Maps (April 2021)","mime":"directory"},"Occult Bestiary":{"basename":"Occult Bestiary","fileperms":"0777","filetype":"dir","filesize":false,"is_readable":true,"is_writeable":true,"is_link":false,"mtime":1617288898,"path":"Occult Bestiary","mime":"directory"},"PDF":{"basename":"PDF","fileperms":"0777","filetype":"dir","filesize":false,"is_readable":true,"is_writeable":true,"is_link":false,"mtime":1617668141,"path":"PDF","mime":"directory"},"PF2e Bestiary 1":{"basename":"PF2e Bestiary 1","fileperms":"0777","filetype":"dir","filesize":false,"is_readable":true,"is_writeable":true,"is_link":false,"mtime":1617664776,"path":"PF2e Bestiary 1","mime":"directory"},"PF2e Bestiary 2":{"basename":"PF2e Bestiary 2","fileperms":"0777","filetype":"dir","filesize":false,"is_readable":true,"is_writeable":true,"is_link":false,"mtime":1617667407,"path":"PF2e Bestiary 2","mime":"directory"},"PF2e Spell Templates by RpSigler":{"basename":"PF2e Spell Templates by RpSigler","fileperms":"0777","filetype":"dir","filesize":false,"is_readable":true,"is_writeable":true,"is_link":false,"mtime":1623260245,"path":"PF2e Spell Templates by RpSigler","mime":"directory"},"Rise of the Runelords":{"basename":"Rise of the Runelords","fileperms":"0777","filetype":"dir","filesize":false,"is_readable":true,"is_writeable":true,"is_link":false,"mtime":1617293243,"path":"Rise of the Runelords","mime":"directory"},"spell-effects":{"basename":"spell-effects","fileperms":"0777","filetype":"dir","filesize":false,"is_readable":true,"is_writeable":true,"is_link":false,"mtime":1630063538,"path":"spell-effects","mime":"directory"}}}