{"basename":"Sunset","fileperms":"0777","filetype":"dir","is_writeable":true,"is_readable":true,"is_link":false,"mime":"directory","mtime":1617628384,"path":"Neutral Maps (April 2021)/Grimy Inn Adept 18x16/Sunset","dirsize":7594895,"files_count":3,"images_count":2,"files":{"Grimy_Inn_Sunset.jpg":{"basename":"Grimy_Inn_Sunset.jpg","fileperms":"0666","filetype":"file","filesize":3164145,"is_readable":true,"is_writeable":true,"is_link":false,"mtime":1604761956,"path":"Neutral Maps (April 2021)/Grimy Inn Adept 18x16/Sunset/Grimy_Inn_Sunset.jpg","ext":"jpg","icon":"image","mime":"image/jpeg","image":{"width":1998,"height":1776,"type":2,"bits":8,"channels":3,"mime":"image/jpeg"}},"Grimy_Inn_Sunset.pdf":{"basename":"Grimy_Inn_Sunset.pdf","fileperms":"0666","filetype":"file","filesize":1355122,"is_readable":true,"is_writeable":true,"is_link":false,"mtime":1604761998,"path":"Neutral Maps (April 2021)/Grimy Inn Adept 18x16/Sunset/Grimy_Inn_Sunset.pdf","ext":"pdf"},"Grimy_Inn_Sunset_Gridless.jpg":{"basename":"Grimy_Inn_Sunset_Gridless.jpg","fileperms":"0666","filetype":"file","filesize":3075628,"is_readable":true,"is_writeable":true,"is_link":false,"mtime":1604761982,"path":"Neutral Maps (April 2021)/Grimy Inn Adept 18x16/Sunset/Grimy_Inn_Sunset_Gridless.jpg","ext":"jpg","icon":"image","mime":"image/jpeg","image":{"width":1998,"height":1776,"type":2,"bits":8,"channels":3,"mime":"image/jpeg"}}}}