{"basename":"Day","fileperms":"0777","filetype":"dir","is_writeable":true,"is_readable":true,"is_link":false,"mime":"directory","mtime":1617628281,"path":"Neutral Maps (April 2021)/Cluttered Warehouse/Day","dirsize":11503108,"files_count":3,"images_count":2,"files":{"Cluttered_Warehouse.jpg":{"basename":"Cluttered_Warehouse.jpg","fileperms":"0666","filetype":"file","filesize":4673470,"is_readable":true,"is_writeable":true,"is_link":false,"mtime":1570290942,"path":"Neutral Maps (April 2021)/Cluttered Warehouse/Day/Cluttered_Warehouse.jpg","ext":"jpg","icon":"image","mime":"image/jpeg","image":{"width":2775,"height":2553,"type":2,"bits":8,"channels":3,"mime":"image/jpeg"}},"Cluttered_Warehouse.pdf":{"basename":"Cluttered_Warehouse.pdf","fileperms":"0666","filetype":"file","filesize":2225730,"is_readable":true,"is_writeable":true,"is_link":false,"mtime":1570291084,"path":"Neutral Maps (April 2021)/Cluttered Warehouse/Day/Cluttered_Warehouse.pdf","ext":"pdf"},"Cluttered_Warehouse_Gridless.jpg":{"basename":"Cluttered_Warehouse_Gridless.jpg","fileperms":"0666","filetype":"file","filesize":4603908,"is_readable":true,"is_writeable":true,"is_link":false,"mtime":1570291063,"path":"Neutral Maps (April 2021)/Cluttered Warehouse/Day/Cluttered_Warehouse_Gridless.jpg","ext":"jpg","icon":"image","mime":"image/jpeg","image":{"width":2775,"height":2553,"type":2,"bits":8,"channels":3,"mime":"image/jpeg"}}}}