{"basename":"Big Camp Adept","fileperms":"0777","filetype":"dir","is_writeable":true,"is_readable":true,"is_link":false,"mime":"directory","mtime":1617628241,"path":"Neutral Maps (April 2021)/Big Camp Adept","dirsize":33832929,"files_count":8,"images_count":6,"files":{"Big_Camp_Outlines.jpg":{"basename":"Big_Camp_Outlines.jpg","fileperms":"0666","filetype":"file","filesize":4245682,"is_readable":true,"is_writeable":true,"is_link":false,"mtime":1533302343,"path":"Neutral Maps (April 2021)/Big Camp Adept/Big_Camp_Outlines.jpg","ext":"jpg","icon":"image","mime":"image/jpeg","image":{"width":4200,"height":4200,"type":2,"bits":8,"channels":3,"mime":"image/jpeg"}},"Big_Camp_Outlines_Gridless.jpg":{"basename":"Big_Camp_Outlines_Gridless.jpg","fileperms":"0666","filetype":"file","filesize":3886325,"is_readable":true,"is_writeable":true,"is_link":false,"mtime":1533302365,"path":"Neutral Maps (April 2021)/Big Camp Adept/Big_Camp_Outlines_Gridless.jpg","ext":"jpg","icon":"image","mime":"image/jpeg","image":{"width":4200,"height":4200,"type":2,"bits":8,"channels":3,"mime":"image/jpeg"}},"Forest_Outcropping_Day.jpg":{"basename":"Forest_Outcropping_Day.jpg","fileperms":"0666","filetype":"file","filesize":4976923,"is_readable":true,"is_writeable":true,"is_link":false,"mtime":1533301773,"path":"Neutral Maps (April 2021)/Big Camp Adept/Forest_Outcropping_Day.jpg","ext":"jpg","icon":"image","mime":"image/jpeg","image":{"width":4200,"height":4200,"type":2,"bits":8,"channels":3,"mime":"image/jpeg"}},"Forest_Outcropping_Day.pdf":{"basename":"Forest_Outcropping_Day.pdf","fileperms":"0666","filetype":"file","filesize":5402859,"is_readable":true,"is_writeable":true,"is_link":false,"mtime":1533301887,"path":"Neutral Maps (April 2021)/Big Camp Adept/Forest_Outcropping_Day.pdf","ext":"pdf"},"Forest_Outcropping_Day_Gridless.jpg":{"basename":"Forest_Outcropping_Day_Gridless.jpg","fileperms":"0666","filetype":"file","filesize":4638338,"is_readable":true,"is_writeable":true,"is_link":false,"mtime":1533301804,"path":"Neutral Maps (April 2021)/Big Camp Adept/Forest_Outcropping_Day_Gridless.jpg","ext":"jpg","icon":"image","mime":"image/jpeg","image":{"width":4200,"height":4200,"type":2,"bits":8,"channels":3,"mime":"image/jpeg"}},"Forest_Outcropping_Night.jpg":{"basename":"Forest_Outcropping_Night.jpg","fileperms":"0666","filetype":"file","filesize":3589595,"is_readable":true,"is_writeable":true,"is_link":false,"mtime":1533301716,"path":"Neutral Maps (April 2021)/Big Camp Adept/Forest_Outcropping_Night.jpg","ext":"jpg","icon":"image","mime":"image/jpeg","image":{"width":4200,"height":4200,"type":2,"bits":8,"channels":3,"mime":"image/jpeg"}},"Forest_Outcropping_Night.pdf":{"basename":"Forest_Outcropping_Night.pdf","fileperms":"0666","filetype":"file","filesize":3819203,"is_readable":true,"is_writeable":true,"is_link":false,"mtime":1533301953,"path":"Neutral Maps (April 2021)/Big Camp Adept/Forest_Outcropping_Night.pdf","ext":"pdf"},"Forest_Outcropping_Night_Gridless.jpg":{"basename":"Forest_Outcropping_Night_Gridless.jpg","fileperms":"0666","filetype":"file","filesize":3274004,"is_readable":true,"is_writeable":true,"is_link":false,"mtime":1533301738,"path":"Neutral Maps (April 2021)/Big Camp Adept/Forest_Outcropping_Night_Gridless.jpg","ext":"jpg","icon":"image","mime":"image/jpeg","image":{"width":4200,"height":4200,"type":2,"bits":8,"channels":3,"mime":"image/jpeg"}}}}